contacts.py
Contacts-1.0.dist-info/LICENSE.txt
Contacts-1.0.dist-info/METADATA
Contacts-1.0.dist-info/WHEEL
Contacts-1.0.dist-info/entry_points.txt
Contacts-1.0.dist-info/top_level.txt
Contacts-1.0.dist-info/RECORD
