Metadata-Version: 2.1
Name: Contacts
Version: 1.0
Summary: Manage your contacts.
Home-page: https://pypi.org/project/Contacts/
Author: Delvian Valentine
Author-email: delvian.valentine@gmail.com
License: UNKNOWN
Project-URL: GitHub, https://github.com/delvianv/Contacts
Keywords: contacts
Platform: UNKNOWN
Classifier: Development Status :: 5 - Production/Stable
Classifier: Environment :: Console
Classifier: Intended Audience :: End Users/Desktop
Classifier: License :: OSI Approved :: GNU General Public License v3 or later (GPLv3+)
Classifier: Natural Language :: English
Classifier: Operating System :: OS Independent
Classifier: Programming Language :: Python :: 3.7
Classifier: Topic :: Utilities
Requires-Python: >=3.7
